jltheme.py
jltheme-0.1.2.dist-info/DESCRIPTION.rst
jltheme-0.1.2.dist-info/METADATA
jltheme-0.1.2.dist-info/RECORD
jltheme-0.1.2.dist-info/WHEEL
jltheme-0.1.2.dist-info/entry_points.txt
jltheme-0.1.2.dist-info/metadata.json
jltheme-0.1.2.dist-info/top_level.txt
