Metadata-Version: 2.0
Name: jltheme
Version: 0.1.2
Summary: Change Matplotlib rcParams to match the current JupyterLab theme.
Home-page: https://github.com/CGCFAD/jltheme
Author: CGCFAD
Author-email: cgcfad@protonmail.com
License: MIT
Platform: UNKNOWN
